[
	{
		"id": 0,
		"shortTitle": "Solar System",
		"question": "What is the largest planet in our solar system?",
		"answers": [
			{
				"id": 0,
				"answer": "Pluto",
				"points": 0
			},
			{
				"id": 1,
				"answer": "Saturn",
				"points": 0
			},
			{
				"id": 2,
				"answer": "Earth",
				"points": 0
			},
			{
				"id": 3,
				"answer": "Jupiter",
				"points": 1
			}
		]
	},
	{
		"id": 1,
		"shortTitle": "Movies",
		"question": "Adele performed the theme song to which James Bond film?",
		"answers": [
			{
				"id": 0,
				"answer": "Casino Royale",
				"points": 0
			},
			{
				"id": 1,
				"answer": "From Russia With Love",
				"points": 0
			},
			{
				"id": 2,
				"answer": "Skyfall",
				"points": 1
			},
			{
				"id": 3,
				"answer": "Quantum of Solace",
				"points": 0
			}
		]
	},
	{
		"id": 2,
		"shortTitle": "Religion",
		"question": "What religion is the most practiced one in India?",
		"answers": [
			{
				"id": 0,
				"answer": "Sikhism",
				"points": 0
			},
			{
				"id": 1,
				"answer": "Islam",
				"points": 0
			},
			{
				"id": 2,
				"answer": "Hinduism",
				"points": 1
			},
			{
				"id": 3,
				"answer": "Shinto",
				"points": 0
			}
		]
	},
	{
		"id": 3,
		"shortTitle": "Music",
		"question": "What funk/soul band was Lionel Richie a member of?",
		"answers": [
			{
				"id": 0,
				"answer": "Amigas",
				"points": 0
			},
			{
				"id": 1,
				"answer": "Commodores",
				"points": 1
			},
			{
				"id": 2,
				"answer": "Spectrums",
				"points": 0
			},
			{
				"id": 3,
				"answer": "Ataris",
				"points": 0
			}
		]
	},
	{
		"id": 4,
		"shortTitle": "Geography",
		"question": "What is the largest country, by area, that has only one time zone?",
		"answers": [
			{
				"id": 0,
				"answer": "Turkey",
				"points": 0
			},
			{
				"id": 1,
				"answer": "Russia",
				"points": 0
			},
			{
				"id": 2,
				"answer": "Australia",
				"points": 0
			},
			{
				"id": 3,
				"answer": "China",
				"points": 1
			}
		]
	}
]
